{"name":"志成zhi_cheng","slug":"blog-author","avatar":"/image/ZCLOGO.jpg","link":"/","description":"一个啥都整的Minecraft玩家 现SLATT成员 17岁 会点JAVA、Python","socials":{"github":"","twitter":"","stackoverflow":"","wechat":"","qq":"","weibo":"","zhihu":"","csdn":"","juejin":"","customs":{"bilibili":{"icon":"/data/svg/bilibili.svg","link":"https://space.bilibili.com/350354944"},"Github":{"icon":"/data/svg/github.svg","link":"https://github.com/zhicheng233"},"QQ":{"icon":"/data/svg/QQ.svg","link":"http://wpa.qq.com/msgrd?v=3&uin=2473367376&site=qq&menu=yes"},"DC":{"icon":"/data/svg/discord.svg","link":"https://discord.gg/Q7jfUne2C5"}}},"post_list":[{"title":"24年通过Telnet获取电信天翼网关超管密码-HS8145C5","uid":"14481fc6a214971b0e61858be70bd50e","slug":"24年通过Telnet获取电信天翼网关超管密码-HS8145C5","date":"2024-02-06T04:40:00.000Z","updated":"2024-02-06T04:44:03.342Z","comments":true,"path":"api/articles/24年通过Telnet获取电信天翼网关超管密码-HS8145C5.json","keywords":null,"cover":[],"text":" 前言家里用的是中国电信诈骗的网自然也是用它的光猫 型号版本为HS8145C5 V5.19.C20S050之前超管的密码一直都是默认的nE7jA%5m，结果24...","permalink":"/post/24年通过Telnet获取电信天翼网关超管密码-HS8145C5","photos":[],"count_time":{"symbolsCount":"2.7k","symbolsTime":"2 mins."},"categories":[],"tags":[{"name":"破解","slug":"破解","count":1,"path":"api/tags/破解.json"},{"name":"网络","slug":"网络","count":1,"path":"api/tags/网络.json"},{"name":"硬件","slug":"硬件","count":1,"path":"api/tags/硬件.json"},{"name":"光猫","slug":"光猫","count":1,"path":"api/tags/光猫.json"},{"name":"骚操作","slug":"骚操作","count":1,"path":"api/tags/骚操作.json"}],"author":{"name":"志成zhi_cheng","slug":"blog-author","avatar":"/image/ZCLOGO.jpg","link":"/","description":"一个啥都整的Minecraft玩家 现SLATT成员 17岁 会点JAVA、Python","socials":{"github":"","twitter":"","stackoverflow":"","wechat":"","qq":"","weibo":"","zhihu":"","csdn":"","juejin":"","customs":{"bilibili":{"icon":"/data/svg/bilibili.svg","link":"https://space.bilibili.com/350354944"},"Github":{"icon":"/data/svg/github.svg","link":"https://github.com/zhicheng233"},"QQ":{"icon":"/data/svg/QQ.svg","link":"http://wpa.qq.com/msgrd?v=3&uin=2473367376&site=qq&menu=yes"},"DC":{"icon":"/data/svg/discord.svg","link":"https://discord.gg/Q7jfUne2C5"}}}},"feature":true},{"title":"浅谈V2rayN & Cloudfare Zero Trust","uid":"59109de0854ca2b0366ba95f91c80871","slug":"浅谈V2ray & Cloudfare Zero Trust","date":"2023-12-08T16:00:00.000Z","updated":"2023-12-16T13:03:59.259Z","comments":true,"path":"api/articles/浅谈V2ray & Cloudfare Zero Trust.json","keywords":null,"cover":"/image/79731173_p0.jpg.png","text":" 前言去年11月份介绍过通过使用 Cloudflare CDN 以达到绕过GFW的方法，但该方法特别挑网站同时效果也不怎么好，本期我们来详细讲讲这个GFW该如何...","permalink":"/post/浅谈V2ray & Cloudfare Zero Trust","photos":[],"count_time":{"symbolsCount":"2.6k","symbolsTime":"2 mins."},"categories":[],"tags":[{"name":"教程","slug":"教程","count":3,"path":"api/tags/教程.json"},{"name":"GFW","slug":"GFW","count":1,"path":"api/tags/GFW.json"},{"name":"软件分享","slug":"软件分享","count":1,"path":"api/tags/软件分享.json"}],"author":{"name":"志成zhi_cheng","slug":"blog-author","avatar":"/image/ZCLOGO.jpg","link":"/","description":"一个啥都整的Minecraft玩家 现SLATT成员 17岁 会点JAVA、Python","socials":{"github":"","twitter":"","stackoverflow":"","wechat":"","qq":"","weibo":"","zhihu":"","csdn":"","juejin":"","customs":{"bilibili":{"icon":"/data/svg/bilibili.svg","link":"https://space.bilibili.com/350354944"},"Github":{"icon":"/data/svg/github.svg","link":"https://github.com/zhicheng233"},"QQ":{"icon":"/data/svg/QQ.svg","link":"http://wpa.qq.com/msgrd?v=3&uin=2473367376&site=qq&menu=yes"},"DC":{"icon":"/data/svg/discord.svg","link":"https://discord.gg/Q7jfUne2C5"}}}},"feature":true},{"title":"树成林 23.11.18","uid":"c3919e686c24f007cafb48a8587fe98c","slug":"树成林 23.11.18","date":"2023-11-19T15:52:51.000Z","updated":"2023-11-25T13:52:10.095Z","comments":true,"path":"api/articles/树成林 23.11.18.json","keywords":null,"cover":null,"text":" 1.不要贪 2.今天作不到的事情，明天照样做不到。 3.掂量的清楚代价得能放得下，革命首先得革自己的命革命首先得革你自己的命。 规划第一个全链路从整体高三的一...","permalink":"/post/树成林 23.11.18","photos":[],"count_time":{"symbolsCount":"2.9k","symbolsTime":"3 mins."},"categories":[],"tags":[{"name":"笔记","slug":"笔记","count":1,"path":"api/tags/笔记.json"}],"author":{"name":"志成zhi_cheng","slug":"blog-author","avatar":"/image/ZCLOGO.jpg","link":"/","description":"一个啥都整的Minecraft玩家 现SLATT成员 17岁 会点JAVA、Python","socials":{"github":"","twitter":"","stackoverflow":"","wechat":"","qq":"","weibo":"","zhihu":"","csdn":"","juejin":"","customs":{"bilibili":{"icon":"/data/svg/bilibili.svg","link":"https://space.bilibili.com/350354944"},"Github":{"icon":"/data/svg/github.svg","link":"https://github.com/zhicheng233"},"QQ":{"icon":"/data/svg/QQ.svg","link":"http://wpa.qq.com/msgrd?v=3&uin=2473367376&site=qq&menu=yes"},"DC":{"icon":"/data/svg/discord.svg","link":"https://discord.gg/Q7jfUne2C5"}}}},"feature":true},{"title":"如何白嫖JetBrains系列软件","uid":"827d5349fcac6148984ade383167eef8","slug":"how-to-crack-JetBrainsTool","date":"2023-02-18T05:17:51.000Z","updated":"2023-02-18T09:36:22.068Z","comments":true,"path":"api/articles/how-to-crack-JetBrainsTool.json","keywords":null,"cover":"/image/a1265432asd.png","text":" 前言JetBrains是一家专注于创建智能开发工具的前沿软件公司，他家的软件用一句话概括就是“JetBrains 出品，必属精品” 但是羊毛来自羊身上，Jet...","permalink":"/post/how-to-crack-JetBrainsTool","photos":[],"count_time":{"symbolsCount":"1.9k","symbolsTime":"2 mins."},"categories":[],"tags":[{"name":"破解 JetBrains","slug":"破解-JetBrains","count":1,"path":"api/tags/破解-JetBrains.json"}],"author":{"name":"志成zhi_cheng","slug":"blog-author","avatar":"/image/ZCLOGO.jpg","link":"/","description":"一个啥都整的Minecraft玩家 现SLATT成员 17岁 会点JAVA、Python","socials":{"github":"","twitter":"","stackoverflow":"","wechat":"","qq":"","weibo":"","zhihu":"","csdn":"","juejin":"","customs":{"bilibili":{"icon":"/data/svg/bilibili.svg","link":"https://space.bilibili.com/350354944"},"Github":{"icon":"/data/svg/github.svg","link":"https://github.com/zhicheng233"},"QQ":{"icon":"/data/svg/QQ.svg","link":"http://wpa.qq.com/msgrd?v=3&uin=2473367376&site=qq&menu=yes"},"DC":{"icon":"/data/svg/discord.svg","link":"https://discord.gg/Q7jfUne2C5"}}}}},{"title":"如何不使用科学上网工具直连访问受限网站","uid":"9da24626d2cf20c945bab22b0f46e148","slug":"How-to-access-restricted-websites-by-direct","date":"2022-11-06T03:53:51.000Z","updated":"2023-02-18T09:36:37.204Z","comments":true,"path":"api/articles/How-to-access-restricted-websites-by-direct.json","keywords":null,"cover":"/image/79731173_p0.jpg.png","text":" 前言又到了一年一度的敏感期，各大梯子供应商该跑的跑，暂停服务的暂停服务，再加上HAX最近不知道发生什么其节点整天爆炸，真的是太难熬了。正好看到隔壁萌幻通过CF...","permalink":"/post/How-to-access-restricted-websites-by-direct","photos":[],"count_time":{"symbolsCount":"1.9k","symbolsTime":"2 mins."},"categories":[],"tags":[{"name":"教程","slug":"教程","count":3,"path":"api/tags/教程.json"}],"author":{"name":"志成zhi_cheng","slug":"blog-author","avatar":"/image/ZCLOGO.jpg","link":"/","description":"一个啥都整的Minecraft玩家 现SLATT成员 17岁 会点JAVA、Python","socials":{"github":"","twitter":"","stackoverflow":"","wechat":"","qq":"","weibo":"","zhihu":"","csdn":"","juejin":"","customs":{"bilibili":{"icon":"/data/svg/bilibili.svg","link":"https://space.bilibili.com/350354944"},"Github":{"icon":"/data/svg/github.svg","link":"https://github.com/zhicheng233"},"QQ":{"icon":"/data/svg/QQ.svg","link":"http://wpa.qq.com/msgrd?v=3&uin=2473367376&site=qq&menu=yes"},"DC":{"icon":"/data/svg/discord.svg","link":"https://discord.gg/Q7jfUne2C5"}}}}},{"title":"如何获取升学E网通的cookie","uid":"9e52d5ecde0b97eabbbe3031c94c0579","slug":"how-to-get-ewt-cookie","date":"2022-08-07T13:52:51.000Z","updated":"2023-02-18T09:36:32.600Z","comments":true,"path":"api/articles/how-to-get-ewt-cookie.json","keywords":null,"cover":[],"text":" 准备工作1.非国产浏览器,如微软的Edge（推荐！！）谷歌的Google Chrome 和火狐2.脑子和手3.5分钟的时间 PS：别再用如360安全&#x2F...","permalink":"/post/how-to-get-ewt-cookie","photos":[],"count_time":{"symbolsCount":611,"symbolsTime":"1 mins."},"categories":[],"tags":[{"name":"教程","slug":"教程","count":3,"path":"api/tags/教程.json"}],"author":{"name":"志成zhi_cheng","slug":"blog-author","avatar":"/image/ZCLOGO.jpg","link":"/","description":"一个啥都整的Minecraft玩家 现SLATT成员 17岁 会点JAVA、Python","socials":{"github":"","twitter":"","stackoverflow":"","wechat":"","qq":"","weibo":"","zhihu":"","csdn":"","juejin":"","customs":{"bilibili":{"icon":"/data/svg/bilibili.svg","link":"https://space.bilibili.com/350354944"},"Github":{"icon":"/data/svg/github.svg","link":"https://github.com/zhicheng233"},"QQ":{"icon":"/data/svg/QQ.svg","link":"http://wpa.qq.com/msgrd?v=3&uin=2473367376&site=qq&menu=yes"},"DC":{"icon":"/data/svg/discord.svg","link":"https://discord.gg/Q7jfUne2C5"}}}}}],"categories":0,"tags":0,"word_count":"13k","post_count":6}